VN_transformer/VN_transformer.py
VN_transformer/__init__.py
VN_transformer/attend.py
VN_transformer/rotations.py
VN_transformer-0.1.0.dist-info/LICENSE
VN_transformer-0.1.0.dist-info/METADATA
VN_transformer-0.1.0.dist-info/WHEEL
VN_transformer-0.1.0.dist-info/top_level.txt
VN_transformer-0.1.0.dist-info/RECORD
