Metadata-Version: 2.1
Name: VN-transformer
Version: 0.1.0
Summary: Vector Neuron Transformer (VN-Transformer)
Home-page: https://github.com/lucidrains/VN-transformer
Author: Phil Wang
Author-email: lucidrains@gmail.com
License: MIT
Keywords: artificial intelligence,deep learning,equivariance,vector neurons,transformers,attention mechanism
Classifier: Development Status :: 4 - Beta
Classifier: Intended Audience :: Developers
Classifier: Topic :: Scientific/Engineering :: Artificial Intelligence
Classifier: License :: OSI Approved :: MIT License
Classifier: Programming Language :: Python :: 3.8
License-File: LICENSE
Requires-Dist: einops (>=0.6.0)
Requires-Dist: torch (>=1.6)
